openspliceai/__init__.py
openspliceai/constants.py
openspliceai/header.py
openspliceai/openspliceai.py
openspliceai/calibrate/__init__.py
openspliceai/calibrate/calibrate.py
openspliceai/calibrate/calibrate_utils.py
openspliceai/calibrate/model_utils.py
openspliceai/calibrate/temperature_scaling.py
openspliceai/calibrate/temperature_scaling_site_only.py
openspliceai/calibrate/visualization.py
openspliceai/create_data/__init__.py
openspliceai/create_data/create_datafile.py
openspliceai/create_data/create_dataset.py
openspliceai/create_data/paralogs.py
openspliceai/create_data/utils.py
openspliceai/create_data/verify_h5_file.py
openspliceai/merge_data/__init__.py
openspliceai/merge_data/merge_dataset.py
openspliceai/predict/__init__.py
openspliceai/predict/predict.py
openspliceai/predict/utils.py
openspliceai/test/__init__.py
openspliceai/test/test.py
openspliceai/train/__init__.py
openspliceai/train/train.py
openspliceai/train_base/__init__.py
openspliceai/train_base/openspliceai.py
openspliceai/train_base/utils.py
openspliceai/transfer/__init__.py
openspliceai/transfer/transfer.py
openspliceai/variant/__init__.py
openspliceai/variant/get_anno.py
openspliceai/variant/utils.py
openspliceai/variant/variant.py
openspliceai-0.0.4.dist-info/LICENSE
openspliceai-0.0.4.dist-info/METADATA
openspliceai-0.0.4.dist-info/WHEEL
openspliceai-0.0.4.dist-info/entry_points.txt
openspliceai-0.0.4.dist-info/top_level.txt
openspliceai-0.0.4.dist-info/RECORD
