Metadata-Version: 2.2
Name: openspliceai
Version: 0.0.4
Summary: Deep learning framework that decodes splicing across species
Home-page: https://github.com/Kuanhao-Chao/OpenSpliceAI
Author: Kuan-Hao Chao
Author-email: kh.chao@cs.jhu.edu
Requires-Python: >=3.9
License-File: LICENSE
Requires-Dist: h5py>=3.9.0
Requires-Dist: numpy>=1.24.4
Requires-Dist: gffutils>=0.12
Requires-Dist: pysam>=0.22.0
Requires-Dist: pandas>=1.5.3
Requires-Dist: pyfaidx>=0.8.1.1
Requires-Dist: tqdm>=4.65.2
Requires-Dist: torch>=2.2.1
Requires-Dist: torchaudio>=2.2.1
Requires-Dist: torchvision>=0.17.1
Requires-Dist: scikit-learn>=1.4.1.post1
Requires-Dist: biopython>=1.83
Requires-Dist: matplotlib>=3.8.3
Requires-Dist: matplotlib-inline>=0.1.7
Requires-Dist: psutil>=5.9.2
Requires-Dist: mappy>=2.28
Dynamic: author
Dynamic: author-email
Dynamic: description
Dynamic: description-content-type
Dynamic: home-page
Dynamic: requires-dist
Dynamic: requires-python
Dynamic: summary
